django_dict_orm/__init__.py
django_dict_orm/base_model.py
django_dict_orm/exception.py
django_dict_orm/fields.py
django_dict_orm/queryset.py
django_dict_orm-0.1.2.dist-info/LICENSE
django_dict_orm-0.1.2.dist-info/METADATA
django_dict_orm-0.1.2.dist-info/WHEEL
django_dict_orm-0.1.2.dist-info/top_level.txt
django_dict_orm-0.1.2.dist-info/RECORD
