Metadata-Version: 2.1
Name: django_dict_orm
Version: 0.1.2
Summary: A lightweight ORM for JSON data storage in Python.
Home-page: https://gitlab.com/mirahmadhacker2007/django-dict-orm.git
Author: Mirahmad
Author-email: mirahmadhacker2007@gmail.com
Classifier: Programming Language :: Python :: 3
Classifier: License :: OSI Approved :: MIT License
Classifier: Operating System :: OS Independent
Requires-Python: >=3.6
License-File: LICENSE
Requires-Dist: bcrypt==4.2.0
Requires-Dist: setuptools==75.2.0
